nobinobi_staff/__init__.py
nobinobi_staff/admin.py
nobinobi_staff/apps.py
nobinobi_staff/fixtures/staff_absence_type_en-us.json
nobinobi_staff/fixtures/staff_absence_type_fr-CH.json
nobinobi_staff/forms.py
nobinobi_staff/locale/de/LC_MESSAGES/django.mo
nobinobi_staff/locale/de/LC_MESSAGES/django.po
nobinobi_staff/locale/en/LC_MESSAGES/django.mo
nobinobi_staff/locale/en/LC_MESSAGES/django.po
nobinobi_staff/locale/fr/LC_MESSAGES/django.mo
nobinobi_staff/locale/fr/LC_MESSAGES/django.po
nobinobi_staff/locale/fr_CH/LC_MESSAGES/django.mo
nobinobi_staff/locale/fr_CH/LC_MESSAGES/django.po
nobinobi_staff/locale/it/LC_MESSAGES/django.mo
nobinobi_staff/locale/it/LC_MESSAGES/django.po
nobinobi_staff/management/__init__.py
nobinobi_staff/management/commands/__init__.py
nobinobi_staff/management/commands/generate_training.py
nobinobi_staff/management/commands/update_training.py
nobinobi_staff/migrations/0001_initial.py
nobinobi_staff/migrations/0002_auto_20181019_1017.py
nobinobi_staff/migrations/0003_auto_20181022_1101.py
nobinobi_staff/migrations/0004_team_order.py
nobinobi_staff/migrations/0005_auto_20181116_0815.py
nobinobi_staff/migrations/0006_staff_working_base.py
nobinobi_staff/migrations/0007_auto_20200221_1138.py
nobinobi_staff/migrations/0008_add_partial_disability.py
nobinobi_staff/migrations/0009_auto_20200805_1143.py
nobinobi_staff/migrations/0010_auto_20201029_1500.py
nobinobi_staff/migrations/__init__.py
nobinobi_staff/models.py
nobinobi_staff/serializers.py
nobinobi_staff/signals.py
nobinobi_staff/static/css/nobinobi_staff.css
nobinobi_staff/static/img/.gitignore
nobinobi_staff/static/js/nobinobi_staff.js
nobinobi_staff/templates/staff/staff_list_readonly.html
nobinobi_staff/tests.py
nobinobi_staff/urls.py
nobinobi_staff/views.py
nobinobi_staff-0.1.6.12.dist-info/AUTHORS.rst
nobinobi_staff-0.1.6.12.dist-info/LICENSE
nobinobi_staff-0.1.6.12.dist-info/METADATA
nobinobi_staff-0.1.6.12.dist-info/WHEEL
nobinobi_staff-0.1.6.12.dist-info/RECORD
